onlyauth/__init__.py
onlyauth/apps.py
onlyauth/authentication.py
onlyauth/sdk.py
onlyauth/sdkconfiguration.py
onlyauth/models/__init__.py
onlyauth/models/components/__init__.py
onlyauth/models/components/security.py
onlyauth/models/errors/__init__.py
onlyauth/models/errors/errorresponse.py
onlyauth/models/errors/sdkerror.py
onlyauth/models/operations/__init__.py
onlyauth/models/operations/createaccesstoken.py
onlyauth/models/operations/deleteapp.py
onlyauth/models/operations/getappbyid.py
onlyauth/models/operations/getapps.py
onlyauth/models/operations/newapp.py
onlyauth/models/operations/updateapp.py
onlyauth/models/operations/validatesuccesstoken.py
onlyauth/utils/__init__.py
onlyauth/utils/retries.py
onlyauth/utils/utils.py
onlyauth-0.0.3.dist-info/LICENSE
onlyauth-0.0.3.dist-info/LICENSE.md
onlyauth-0.0.3.dist-info/METADATA
onlyauth-0.0.3.dist-info/WHEEL
onlyauth-0.0.3.dist-info/top_level.txt
onlyauth-0.0.3.dist-info/RECORD
