Metadata-Version: 2.1
Name: onlyauth
Version: 0.0.3
Summary: OnlyAuth Python Library to quickly and easily add 2FA to your website/app
Home-page: https://www.onlyauth.io
Author: OnlyAuth
Project-URL: Source, https://github.com/onlyauth-io/onlyauth-python
Keywords: 2fa,mfa,two factor auth,2fa api
Requires-Python: >=3.8
License-File: LICENSE
License-File: LICENSE.md
Requires-Dist: certifi (>=2023.7.22)
Requires-Dist: charset-normalizer (>=3.2.0)
Requires-Dist: dataclasses-json-speakeasy (>=0.5.11)
Requires-Dist: idna (>=3.4)
Requires-Dist: jsonpath-python (>=1.0.6)
Requires-Dist: marshmallow (>=3.19.0)
Requires-Dist: mypy-extensions (>=1.0.0)
Requires-Dist: packaging (>=23.1)
Requires-Dist: python-dateutil (>=2.8.2)
Requires-Dist: requests (>=2.31.0)
Requires-Dist: six (>=1.16.0)
Requires-Dist: typing-inspect (>=0.9.0)
Requires-Dist: typing-extensions (>=4.7.1)
Requires-Dist: urllib3 (>=1.26.18)
Provides-Extra: dev
Requires-Dist: pylint (==2.16.2) ; extra == 'dev'
